{"is_source_file": true, "format": "HTML", "description": "Basic HTML template for a React frontend application named 'KAVIA App', with links to stylesheets, favicon, and manifest, and a root div for rendering the app frontend.", "external_files": ["%PUBLIC_URL%/favicon.ico", "%PUBLIC_URL%/logo192.png", "%PUBLIC_URL%/manifest.json", "https://fonts.googleapis.com/css2?family=Inter:wght@400;500;600;700&display=swap"], "external_methods": [], "published": [], "classes": [], "methods": [], "calls": [], "search-terms": ["index.html", "public folder", "React app template", "font loading", "favicon", "manifest.json", "root div", "public URL"], "state": 2, "file_id": 2, "knowledge_revision": 19, "git_revision": "e23e5997b5cb4a1bee008df616765adb247dcece", "hash": "d2b40d02d5f7873d8a6713bad837edd4", "format-version": 4, "code-base-name": "notes_frontend", "filename": "notes_frontend/public/index.html", "revision_history": [{"19": "e23e5997b5cb4a1bee008df616765adb247dcece"}]}